{"sUbA98Bqa6Gfilbq/aLa/g==":"background1.jpg","hzVuoKB4RfqJogz0t5yTAA==":"mbr-1631x1080.jpg","pJkNfERdJqXCuVlpYZ6SKQ==":"banner_iisue-1138x126.png","0X+zxGpuF3HR2UxKw3duXA==":"banner_posg-1138x126.png","aQN2wqWehaD6D4VLgid2fQ==":"dia1a-784x398.png","jYzJSiCieLLrBiv20BEreA==":"dia2a-784x398.png","oBRi83/DdqpC2wfKk08+8A==":"dia3a-784x398.png","0gn/0WbJ2DsXTZtlNalpqQ==":"bookshelf-847x682.jpg","eH382tULonixai8UOi345A==":"banner_posg-1-1138x126.png","9L6ydP2ejIKELXsGTgkSYw==":"espanapoliticas_carrusel-1-1960x600.jpg","OZuOCnr1NQB0CK3p5RNiPg==":"banner_posg2-1000x126.png"}